LICENSE
MANIFEST.in
README.md
setup.cfg
setup.py
unqlitepy/Makefile
unqlitepy/__init__.py
unqlitepy/_unqlite.py
unqlitepy/unqlite.c
unqlitepy/unqlite.h
unqlitepy.egg-info/PKG-INFO
unqlitepy.egg-info/SOURCES.txt
unqlitepy.egg-info/dependency_links.txt
unqlitepy.egg-info/not-zip-safe
unqlitepy.egg-info/requires.txt
unqlitepy.egg-info/top_level.txt