Metadata-Version: 1.1
Name: unqlitepy
Version: 0.3.0
Summary: UnQLite Binding for Python
Home-page: https://github.com/nobonobo/unqlitepy
Author: Noboru Irieda
Author-email: noboru@irieda.com
License: BSD
Keywords: database,kvs,unqlite
Platform: UNKNOWN
Classifier: Development Status :: 3 - Alpha
Classifier: Topic :: Database
Classifier: License :: OSI Approved :: BSD License
Classifier: Operating System :: POSIX
Classifier: Operating System :: Unix
Classifier: Operating System :: MacOS
Requires: ctypesgen
